setup.py
sns007_distributions/Binomialdistribution.py
sns007_distributions/Gaussiandistribution.py
sns007_distributions/Generaldistribution.py
sns007_distributions/__init__.py
sns007_distributions.egg-info/PKG-INFO
sns007_distributions.egg-info/SOURCES.txt
sns007_distributions.egg-info/dependency_links.txt
sns007_distributions.egg-info/not-zip-safe
sns007_distributions.egg-info/top_level.txt