Metadata-Version: 1.0
Name: sns007-distributions
Version: 1.2
Summary: sns007: Gaussian and Binomial distributions
Home-page: UNKNOWN
Author: Somesh Saini1970
Author-email: somesh.saini1970@gmail.com
License: UNKNOWN
Platform: UNKNOWN
